setup.py
ccp_sde_parser/__init__.py
ccp_sde_parser/bigqueryize.py
ccp_sde_parser/csvize.py
ccp_sde_parser/merge_ccp_yaml.py
ccp_sde_parser/schema_converter.py
ccp_sde_parser/split_tables.py
ccp_sde_parser/sqlize.py
ccp_sde_parser.egg-info/PKG-INFO
ccp_sde_parser.egg-info/SOURCES.txt
ccp_sde_parser.egg-info/dependency_links.txt
ccp_sde_parser.egg-info/entry_points.txt
ccp_sde_parser.egg-info/requires.txt
ccp_sde_parser.egg-info/top_level.txt