Metadata-Version: 1.0
Name: ccp_sde_parser
Version: 1.0.1
Summary: EVE Online Static Dump Export Parser. Works with https://github.com/eve-val/dump_extractor
Home-page: https://github.com/eve-val/dump-parser
Author: Silas Snider
Author-email: swsnider@gmail.com
License: BSD
Keywords: EVE Online Static Dump Export Parser
Platform: UNKNOWN
Classifier: Development Status :: 3 - Alpha
Classifier: Topic :: Utilities
Classifier: License :: OSI Approved :: BSD License
